primeqa/__init__.py
primeqa/boolqa/__init__.py
primeqa/boolqa/run_score_normalizer.py
primeqa/boolqa/processors/__init__.py
primeqa/boolqa/processors/dataset/__init__.py
primeqa/boolqa/processors/dataset/mrc2dataset.py
primeqa/boolqa/score_normalizer/__init__.py
primeqa/boolqa/score_normalizer/score_normalizer.py
primeqa/calibration/__init__.py
primeqa/calibration/confidence_scorer.py
primeqa/calibration/train_confidence_calibrator.py
primeqa/components/__init__.py
primeqa/components/base.py
primeqa/components/embeddings/__init__.py
primeqa/components/embeddings/dpr_embeddings.py
primeqa/components/indexer/__init__.py
primeqa/components/indexer/dense.py
primeqa/components/indexer/sparse.py
primeqa/components/reader/LLMService.py
primeqa/components/reader/__init__.py
primeqa/components/reader/extractive.py
primeqa/components/reader/generative.py
primeqa/components/reader/prompt.py
primeqa/components/reader/reader_factory.py
primeqa/components/reranker/__init__.py
primeqa/components/reranker/colbert_reranker.py
primeqa/components/reranker/dpr_reranker.py
primeqa/components/reranker/seq_classification_reranker.py
primeqa/components/retriever/__init__.py
primeqa/components/retriever/dense.py
primeqa/components/retriever/searchable_corpus.py
primeqa/components/retriever/sparse.py
primeqa/distillation/__init__.py
primeqa/distillation/distillation.py
primeqa/ir/__init__.py
primeqa/ir/run_bm25_retrieval.py
primeqa/ir/run_ir.py
primeqa/ir/dense/__init__.py
primeqa/ir/dense/colbert_top/__init__.py
primeqa/ir/dense/colbert_top/setup.py
primeqa/ir/dense/colbert_top/colbert/__init__.py
primeqa/ir/dense/colbert_top/colbert/index.py
primeqa/ir/dense/colbert_top/colbert/indexer.py
primeqa/ir/dense/colbert_top/colbert/parameters.py
primeqa/ir/dense/colbert_top/colbert/run_indexer.py
primeqa/ir/dense/colbert_top/colbert/run_searcher.py
primeqa/ir/dense/colbert_top/colbert/run_trainer.py
primeqa/ir/dense/colbert_top/colbert/searcher.py
primeqa/ir/dense/colbert_top/colbert/trainer.py
primeqa-0.15.2.dist-info/LICENSE
primeqa-0.15.2.dist-info/METADATA
primeqa-0.15.2.dist-info/WHEEL
primeqa-0.15.2.dist-info/top_level.txt
primeqa-0.15.2.dist-info/RECORD
