Metadata-Version: 2.1
Name: primeqa
Version: 0.15.2
Summary: State-of-the-art Question Answering
Home-page: https://github.com/primeqa/primeqa
Author: PrimeQA Team
Author-email: primeqa@us.ibm.com
License: Apache
Keywords: Question Answering (QA),Machine Reading Comprehension (MRC),Information Retrieval (IR)
Classifier: Development Status :: 3 - Alpha
Classifier: Intended Audience :: Developers
Classifier: Intended Audience :: Science/Research
Classifier: Programming Language :: Python :: 3
Requires-Python: >=3.7.0, <3.11.0
License-File: LICENSE
Requires-Dist: bitarray (~=2.3.7)
Requires-Dist: click (~=8.0.4)
Requires-Dist: datasets[apache-beam] (~=2.3.2)
Requires-Dist: faiss-cpu (~=1.7.2)
Requires-Dist: gitpython (~=3.1.27)
Requires-Dist: jsonlines (~=3.0.0)
Requires-Dist: ninja (~=1.10.2.3)
Requires-Dist: numpy (~=1.21.5)
Requires-Dist: packaging (~=21.3)
Requires-Dist: pandas (~=1.4.0)
Requires-Dist: psutil (~=5.9.0)
Requires-Dist: pyarrow (~=7.0.0)
Requires-Dist: pyserini (~=0.20.0)
Requires-Dist: scikit-learn (~=1.0.2)
Requires-Dist: signals (~=0.0.2)
Requires-Dist: stanza (~=1.4.0)
Requires-Dist: torch (~=1.11.0)
Requires-Dist: transformers (~=4.24.0)
Requires-Dist: sentence-transformers
Requires-Dist: tensorboard
Requires-Dist: sentencepiece (~=0.1.96)
Requires-Dist: ujson (~=5.1.0)
Requires-Dist: tqdm (~=4.64.0)
Requires-Dist: frozendict
Requires-Dist: nlp
Requires-Dist: protobuf (~=3.20.0)
Requires-Dist: tabulate (~=0.8.9)
Requires-Dist: rouge-score
Requires-Dist: rouge (~=1.0.1)
Requires-Dist: grpcio (~=1.48.1)
Requires-Dist: grpcio-tools (~=1.48.1)
Requires-Dist: fastapi (~=0.85.0)
Requires-Dist: uvicorn (~=0.18.0)
Requires-Dist: cachetools (~=5.2.0)
Requires-Dist: sqlitedict (~=2.0.0)
Requires-Dist: openai (~=0.27.0)
Requires-Dist: nltk (~=3.8.1)
Provides-Extra: all
Requires-Dist: docutils (<0.18,>=0.14) ; extra == 'all'
Requires-Dist: bitarray (~=2.3.7) ; extra == 'all'
Requires-Dist: bump2version (~=1.0.1) ; extra == 'all'
Requires-Dist: click (~=8.0.4) ; extra == 'all'
Requires-Dist: datasets[apache-beam] (~=2.3.2) ; extra == 'all'
Requires-Dist: faiss-cpu (~=1.7.2) ; extra == 'all'
Requires-Dist: faiss-gpu (~=1.7.2) ; extra == 'all'
Requires-Dist: gitpython (~=3.1.27) ; extra == 'all'
Requires-Dist: ipykernel (~=6.13.0) ; extra == 'all'
Requires-Dist: ipywidgets (~=7.7.0) ; extra == 'all'
Requires-Dist: jsonlines (~=3.0.0) ; extra == 'all'
Requires-Dist: ninja (~=1.10.2.3) ; extra == 'all'
Requires-Dist: numpy (~=1.21.5) ; extra == 'all'
Requires-Dist: packaging (~=21.3) ; extra == 'all'
Requires-Dist: pandas (~=1.4.0) ; extra == 'all'
Requires-Dist: psutil (~=5.9.0) ; extra == 'all'
Requires-Dist: pyarrow (~=7.0.0) ; extra == 'all'
Requires-Dist: pyserini (~=0.20.0) ; extra == 'all'
Requires-Dist: pytest (~=7.1.1) ; extra == 'all'
Requires-Dist: pytest-cov (~=3.0.0) ; extra == 'all'
Requires-Dist: pytest-mock (~=3.7.0) ; extra == 'all'
Requires-Dist: pytest-rerunfailures (~=10.2) ; extra == 'all'
Requires-Dist: scikit-learn (~=1.0.2) ; extra == 'all'
Requires-Dist: signals (~=0.0.2) ; extra == 'all'
Requires-Dist: stanza (~=1.4.0) ; extra == 'all'
Requires-Dist: torch (~=1.11.0) ; extra == 'all'
Requires-Dist: tox (~=3.24.5) ; extra == 'all'
Requires-Dist: transformers (~=4.24.0) ; extra == 'all'
Requires-Dist: sentence-transformers ; extra == 'all'
Requires-Dist: tensorboard ; extra == 'all'
Requires-Dist: sentencepiece (~=0.1.96) ; extra == 'all'
Requires-Dist: ujson (~=5.1.0) ; extra == 'all'
Requires-Dist: tqdm (~=4.64.0) ; extra == 'all'
Requires-Dist: frozendict ; extra == 'all'
Requires-Dist: nlp ; extra == 'all'
Requires-Dist: protobuf (~=3.20.0) ; extra == 'all'
Requires-Dist: tabulate (~=0.8.9) ; extra == 'all'
Requires-Dist: rouge-score ; extra == 'all'
Requires-Dist: rouge (~=1.0.1) ; extra == 'all'
Requires-Dist: myst-parser (~=0.17.2) ; extra == 'all'
Requires-Dist: pydata-sphinx-theme (~=0.9.0) ; extra == 'all'
Requires-Dist: sphinx (~=4.4.0) ; extra == 'all'
Requires-Dist: sphinx-design (~=0.2.0) ; extra == 'all'
Requires-Dist: recommonmark (~=0.7.1) ; extra == 'all'
Requires-Dist: grpcio (~=1.48.1) ; extra == 'all'
Requires-Dist: grpcio-tools (~=1.48.1) ; extra == 'all'
Requires-Dist: fastapi (~=0.85.0) ; extra == 'all'
Requires-Dist: uvicorn (~=0.18.0) ; extra == 'all'
Requires-Dist: cachetools (~=5.2.0) ; extra == 'all'
Requires-Dist: sqlitedict (~=2.0.0) ; extra == 'all'
Requires-Dist: openai (~=0.27.0) ; extra == 'all'
Requires-Dist: nltk (~=3.8.1) ; extra == 'all'
Provides-Extra: dev
Requires-Dist: bump2version (~=1.0.1) ; extra == 'dev'
Provides-Extra: docs
Requires-Dist: myst-parser (~=0.17.2) ; extra == 'docs'
Requires-Dist: pydata-sphinx-theme (~=0.9.0) ; extra == 'docs'
Requires-Dist: sphinx (~=4.4.0) ; extra == 'docs'
Requires-Dist: sphinx-design (~=0.2.0) ; extra == 'docs'
Requires-Dist: recommonmark (~=0.7.1) ; extra == 'docs'
Provides-Extra: gpu
Requires-Dist: bitarray (~=2.3.7) ; extra == 'gpu'
Requires-Dist: click (~=8.0.4) ; extra == 'gpu'
Requires-Dist: datasets[apache-beam] (~=2.3.2) ; extra == 'gpu'
Requires-Dist: faiss-cpu (~=1.7.2) ; extra == 'gpu'
Requires-Dist: faiss-gpu (~=1.7.2) ; extra == 'gpu'
Requires-Dist: gitpython (~=3.1.27) ; extra == 'gpu'
Requires-Dist: jsonlines (~=3.0.0) ; extra == 'gpu'
Requires-Dist: ninja (~=1.10.2.3) ; extra == 'gpu'
Requires-Dist: numpy (~=1.21.5) ; extra == 'gpu'
Requires-Dist: packaging (~=21.3) ; extra == 'gpu'
Requires-Dist: pandas (~=1.4.0) ; extra == 'gpu'
Requires-Dist: psutil (~=5.9.0) ; extra == 'gpu'
Requires-Dist: pyarrow (~=7.0.0) ; extra == 'gpu'
Requires-Dist: pyserini (~=0.20.0) ; extra == 'gpu'
Requires-Dist: scikit-learn (~=1.0.2) ; extra == 'gpu'
Requires-Dist: signals (~=0.0.2) ; extra == 'gpu'
Requires-Dist: stanza (~=1.4.0) ; extra == 'gpu'
Requires-Dist: torch (~=1.11.0) ; extra == 'gpu'
Requires-Dist: transformers (~=4.24.0) ; extra == 'gpu'
Requires-Dist: sentence-transformers ; extra == 'gpu'
Requires-Dist: tensorboard ; extra == 'gpu'
Requires-Dist: sentencepiece (~=0.1.96) ; extra == 'gpu'
Requires-Dist: tqdm (~=4.64.0) ; extra == 'gpu'
Requires-Dist: frozendict ; extra == 'gpu'
Requires-Dist: nlp ; extra == 'gpu'
Requires-Dist: protobuf (~=3.20.0) ; extra == 'gpu'
Requires-Dist: tabulate (~=0.8.9) ; extra == 'gpu'
Requires-Dist: rouge-score ; extra == 'gpu'
Requires-Dist: grpcio (~=1.48.1) ; extra == 'gpu'
Requires-Dist: grpcio-tools (~=1.48.1) ; extra == 'gpu'
Requires-Dist: fastapi (~=0.85.0) ; extra == 'gpu'
Requires-Dist: uvicorn (~=0.18.0) ; extra == 'gpu'
Requires-Dist: cachetools (~=5.2.0) ; extra == 'gpu'
Requires-Dist: sqlitedict (~=2.0.0) ; extra == 'gpu'
Requires-Dist: openai (~=0.27.0) ; extra == 'gpu'
Requires-Dist: nltk (~=3.8.1) ; extra == 'gpu'
Provides-Extra: install
Requires-Dist: bitarray (~=2.3.7) ; extra == 'install'
Requires-Dist: click (~=8.0.4) ; extra == 'install'
Requires-Dist: datasets[apache-beam] (~=2.3.2) ; extra == 'install'
Requires-Dist: faiss-cpu (~=1.7.2) ; extra == 'install'
Requires-Dist: gitpython (~=3.1.27) ; extra == 'install'
Requires-Dist: jsonlines (~=3.0.0) ; extra == 'install'
Requires-Dist: ninja (~=1.10.2.3) ; extra == 'install'
Requires-Dist: numpy (~=1.21.5) ; extra == 'install'
Requires-Dist: packaging (~=21.3) ; extra == 'install'
Requires-Dist: pandas (~=1.4.0) ; extra == 'install'
Requires-Dist: psutil (~=5.9.0) ; extra == 'install'
Requires-Dist: pyarrow (~=7.0.0) ; extra == 'install'
Requires-Dist: pyserini (~=0.20.0) ; extra == 'install'
Requires-Dist: scikit-learn (~=1.0.2) ; extra == 'install'
Requires-Dist: signals (~=0.0.2) ; extra == 'install'
Requires-Dist: stanza (~=1.4.0) ; extra == 'install'
Requires-Dist: torch (~=1.11.0) ; extra == 'install'
Requires-Dist: transformers (~=4.24.0) ; extra == 'install'
Requires-Dist: sentence-transformers ; extra == 'install'
Requires-Dist: tensorboard ; extra == 'install'
Requires-Dist: sentencepiece (~=0.1.96) ; extra == 'install'
Requires-Dist: ujson (~=5.1.0) ; extra == 'install'
Requires-Dist: tqdm (~=4.64.0) ; extra == 'install'
Requires-Dist: frozendict ; extra == 'install'
Requires-Dist: nlp ; extra == 'install'
Requires-Dist: protobuf (~=3.20.0) ; extra == 'install'
Requires-Dist: tabulate (~=0.8.9) ; extra == 'install'
Requires-Dist: rouge-score ; extra == 'install'
Requires-Dist: rouge (~=1.0.1) ; extra == 'install'
Requires-Dist: grpcio (~=1.48.1) ; extra == 'install'
Requires-Dist: grpcio-tools (~=1.48.1) ; extra == 'install'
Requires-Dist: fastapi (~=0.85.0) ; extra == 'install'
Requires-Dist: uvicorn (~=0.18.0) ; extra == 'install'
Requires-Dist: cachetools (~=5.2.0) ; extra == 'install'
Requires-Dist: sqlitedict (~=2.0.0) ; extra == 'install'
Requires-Dist: openai (~=0.27.0) ; extra == 'install'
Requires-Dist: nltk (~=3.8.1) ; extra == 'install'
Provides-Extra: notebooks
Requires-Dist: ipykernel (~=6.13.0) ; extra == 'notebooks'
Requires-Dist: ipywidgets (~=7.7.0) ; extra == 'notebooks'
Provides-Extra: tests
Requires-Dist: docutils (<0.18,>=0.14) ; extra == 'tests'
Requires-Dist: pytest (~=7.1.1) ; extra == 'tests'
Requires-Dist: pytest-cov (~=3.0.0) ; extra == 'tests'
Requires-Dist: pytest-mock (~=3.7.0) ; extra == 'tests'
Requires-Dist: pytest-rerunfailures (~=10.2) ; extra == 'tests'
Requires-Dist: tox (~=3.24.5) ; extra == 'tests'
